patoka/__init__.py
patoka/backend_design.py
patoka/backend_prep.py
patoka/circuit_data_prep.py
patoka/draw_uncertainty.py
patoka/esp.py
patoka/get_fake_backend.py
patoka/image_convolution_utils.py
patoka/job_output_data.py
patoka/machine_data_prep.py
patoka/machine_data_processing.py
patoka/machine_viewer_meta.py
patoka/match_circuit.py
patoka/process_job_data.py
patoka/process_pulse_data.py
patoka/qiskit_draw_utils.py
patoka/retrieve_job_data.py
patoka/shors_utils.py
patoka/transpile_params.py
patoka/widget_classes.py
patoka/widgets.py
patoka/widgets_dev.py
patoka/widget_built/index.js
patoka/widget_built/style.css
patoka-0.2.16.dist-info/LICENSE
patoka-0.2.16.dist-info/METADATA
patoka-0.2.16.dist-info/WHEEL
patoka-0.2.16.dist-info/top_level.txt
patoka-0.2.16.dist-info/RECORD
