Metadata-Version: 2.2
Name: patoka
Version: 0.2.16
Summary: A collection of Jupyter Lab widgets for IBM Qiskit
Author: Hyeok Kim, Mingyoung J. Jeng, Kaitlin N. Smith
Project-URL: Homepage, https://github.com/see-mike-out/patoka
Project-URL: Issues, https://github.com/see-mike-out/patoka/issues
Requires-Python: >=3.9
License-File: LICENSE
Requires-Dist: qiskit>=1.3
Requires-Dist: qiskit-aer>=0.16
Requires-Dist: qiskit_ibm_runtime>=0.34
Requires-Dist: qiskit_algorithms>=0.3
Requires-Dist: qiskit_machine_learning>=0.8
Requires-Dist: numpy>=2.0
Requires-Dist: pandas>=2.2
Requires-Dist: altair>=5.5
Requires-Dist: scipy>=1.13
Requires-Dist: tqdm>=4.67
Requires-Dist: jupyter>=1.1
Requires-Dist: anywidget>=0.9
Requires-Dist: matplotlib>=3.9
